<?xml version="1.0" encoding="UTF-8"?>
<!DOCTYPE hibernate-mapping PUBLIC "-//Hibernate/Hibernate Mapping DTD 3.0//EN" "http://hibernate.sourceforge.net/hibernate-mapping-3.0.dtd">
<hibernate-mapping>
	<class name="br.edu.ifpr.comat.model.Estado" table="Estado"
		catalog="comat">
		<id name="uf" type="string">
			<column name="uf" length="2" />
			<generator class="assigned" />
		</id>
		<property name="nome" type="string">
			<column name="nome" length="22" not-null="true" unique="true" />
		</property>
	</class>
</hibernate-mapping>
