<?xml version="1.0"?>
<!DOCTYPE hibernate-mapping PUBLIC "-//Hibernate/Hibernate Mapping DTD 3.0//EN"
"http://hibernate.sourceforge.net/hibernate-mapping-3.0.dtd">
<!-- Generated 23/09/2013 21:24:33 by Hibernate Tools 3.2.1.GA -->
<hibernate-mapping>
    <class name="br.edu.ifpr.comat.entity.TbPessoaFisica" table="TB_PessoaFisica" catalog="comat">
        <id name="cpfPfi" type="long">
            <column name="CPF_Pfi" />
            <generator class="assigned" />
        </id>
        <property name="rgPfi" type="int">
            <column name="RG_Pfi" not-null="true" />
        </property>
        <property name="nomePfi" type="string">
            <column name="Nome_Pfi" length="72" not-null="true" />
        </property>
        <property name="dataNascPfi" type="date">
            <column name="DataNasc_Pfi" length="10" />
        </property>
        <property name="celularCli" type="string">
            <column name="Celular_Cli" length="12" />
        </property>
        <property name="idCli" type="int">
            <column name="ID_Cli" not-null="true" />
        </property>
    </class>
</hibernate-mapping>
